muppy/__init__.py
muppy/main.py
muppy-1.0.2.dist-info/METADATA
muppy-1.0.2.dist-info/WHEEL
muppy-1.0.2.dist-info/entry_points.txt
muppy-1.0.2.dist-info/licenses/LICENSE
muppy-1.0.2.dist-info/RECORD
