Metadata-Version: 2.4
Name: muppy
Version: 1.0.2
Summary: Markup Preprocessor for Python
Project-URL: Repository, https://codeberg.org/screwery/muppy
Project-URL: Issues, https://codeberg.org/screwery/muppy/issues
Project-URL: Changelog, https://codeberg.org/screwery/muppy/src/branch/main/CHANGELOG.md
Author-email: Ellie Viesná <snowboard_refinery@proton.me>
License: MIT License
License-File: LICENSE
Keywords: c,markup,preprocessor,shell,tex,xml
Classifier: Development Status :: 4 - Beta
Classifier: Environment :: Console
Classifier: License :: OSI Approved :: MIT License
Classifier: Natural Language :: English
Classifier: Operating System :: OS Independent
Classifier: Programming Language :: Python :: 3.12
Requires-Python: >=3.12
Requires-Dist: argparse
